nox/__init__.py
nox/__main__.py
nox/_option_set.py
nox/_options.py
nox/_parametrize.py
nox/command.py
nox/logger.py
nox/manifest.py
nox/popen.py
nox/registry.py
nox/sessions.py
nox/tasks.py
nox/tox_to_nox.jinja2
nox/tox_to_nox.py
nox/virtualenv.py
nox/workflow.py
nox_py2-2019.6.25.dist-info/LICENSE
nox_py2-2019.6.25.dist-info/METADATA
nox_py2-2019.6.25.dist-info/WHEEL
nox_py2-2019.6.25.dist-info/entry_points.txt
nox_py2-2019.6.25.dist-info/top_level.txt
nox_py2-2019.6.25.dist-info/RECORD
